masogram/__init__.py
masogram/exceptions.py
masogram/loggers.py
masogram/py.typed
masogram/client/__init__.py
masogram/client/bot.py
masogram/client/telegram.py
masogram/client/session/__init__.py
masogram/client/session/aiohttp.py
masogram/client/session/base.py
masogram/client/session/middlewares/__init__.py
masogram/client/session/middlewares/base.py
masogram/client/session/middlewares/manager.py
masogram/client/session/middlewares/request_logging.py
masogram/dispatcher/__init__.py
masogram/dispatcher/dispatcher.py
masogram/dispatcher/flags.py
masogram/dispatcher/router.py
masogram/dispatcher/event/__init__.py
masogram/dispatcher/event/bases.py
masogram/dispatcher/event/event.py
masogram/dispatcher/event/handler.py
masogram/dispatcher/event/telegram.py
masogram/dispatcher/middlewares/__init__.py
masogram/dispatcher/middlewares/base.py
masogram/dispatcher/middlewares/error.py
masogram/dispatcher/middlewares/manager.py
masogram/dispatcher/middlewares/user_context.py
masogram/enums/__init__.py
masogram/enums/bot_command_scope_type.py
masogram/enums/chat_action.py
masogram/enums/chat_member_status.py
masogram/enums/chat_type.py
masogram/enums/content_type.py
masogram/enums/dice_emoji.py
masogram/enums/inline_query_result_type.py
masogram/enums/input_media_type.py
masogram/enums/mask_position_point.py
masogram/enums/menu_button_type.py
masogram/enums/message_entity_type.py
masogram/enums/parse_mode.py
masogram/enums/poll_type.py
masogram/enums/sticker_format.py
masogram/enums/sticker_type.py
masogram/enums/topic_icon_color.py
masogram/enums/update_type.py
masogram/filters/__init__.py
masogram/filters/base.py
masogram/filters/callback_data.py
masogram/filters/chat_member_updated.py
masogram/filters/command.py
masogram/filters/exception.py
masogram/filters/logic.py
masogram/filters/magic_data.py
masogram/filters/state.py
masogram/fsm/__init__.py
masogram/fsm/context.py
masogram/fsm/middleware.py
masogram/fsm/state.py
masogram/fsm/strategy.py
masogram-1.0.dist-info/METADATA
masogram-1.0.dist-info/WHEEL
masogram-1.0.dist-info/licenses/LICENSE
masogram-1.0.dist-info/RECORD
